serbian_py/__init__.py
serbian_py/main_commands.py
serbian_py-0.1.5.dist-info/licenses/LICENSE
serbian_py-0.1.5.dist-info/METADATA
serbian_py-0.1.5.dist-info/WHEEL
serbian_py-0.1.5.dist-info/top_level.txt
serbian_py-0.1.5.dist-info/RECORD
