Metadata-Version: 2.4
Name: serbian-py
Version: 0.1.5
Summary: Serbian language adaptations and utility functions for Python programming
Author-email: Pavle012 <pavle.tomic.32300@gmail.com>
License-Expression: MIT
Project-URL: Repository, https://github.com/Pavle012/serbian_py
Project-URL: Homepage, https://github.com/Pavle012/serbian_py
Keywords: serbian,language,utilities,education
Classifier: Development Status :: 3 - Alpha
Classifier: Intended Audience :: Education
Classifier: Natural Language :: Serbian
Classifier: Programming Language :: Python :: 3
Classifier: Programming Language :: Python :: 3.8
Classifier: Programming Language :: Python :: 3.9
Classifier: Programming Language :: Python :: 3.10
Classifier: Programming Language :: Python :: 3.11
Classifier: Programming Language :: Python :: 3.12
Requires-Python: >=3.8
License-File: LICENSE
Dynamic: license-file
